navel/__init__.py
navel/_async.py
navel/_data_structs.py
navel/_interface.py
navel/_messages.py
navel/_socket_coms.py
navel/_version.py
navel/_pyproto/__init__.py
navel/_pyproto/cns_pb2.py
navel/_pyproto/config_pb2.py
navel/_pyproto/coord_pb2.py
navel/_pyproto/klframe_pb2.py
navel/_pyproto/payload_pb2.py
navel/_pyproto/perc_pb2.py
navel/_pyproto/speech_pb2.py
navel/_pyproto/sys_pb2.py
navel-0.10.0.dist-info/licenses/LICENSE
navel-0.10.0.dist-info/METADATA
navel-0.10.0.dist-info/WHEEL
navel-0.10.0.dist-info/top_level.txt
navel-0.10.0.dist-info/RECORD
