Metadata-Version: 2.4
Name: navel
Version: 0.10.0
Summary: SDK for the Navel platform
Author-email: navel robotics GmbH <info@navelrobotics.com>
Project-URL: Homepage, https://navelrobotics.com
Project-URL: Documentation, https://doc.navelrobotics.com/
Classifier: Programming Language :: Python :: 3
Classifier: Operating System :: POSIX :: Linux
Requires-Python: >=3.11
License-File: LICENSE
Requires-Dist: pyalsaaudio
Requires-Dist: bitstring
Requires-Dist: protobuf
Dynamic: license-file
